kojo/__init__.py
kojo/extra.py
kojo/item.py
kojo/process.py
kojo/py.typed
kojo-0.28.1.dist-info/LICENSE.txt
kojo-0.28.1.dist-info/METADATA
kojo-0.28.1.dist-info/WHEEL
kojo-0.28.1.dist-info/top_level.txt
kojo-0.28.1.dist-info/RECORD
