Metadata-Version: 2.1
Name: kojo
Version: 0.28.1
Summary: A library to transform data through a pipeline
Author-email: Olaf Schneider <mail@olafschneider.com>
License: GNU GPLv3
Project-URL: Repository, https://gitlab.com/filchos/kojo
Classifier: Development Status :: 4 - Beta
Classifier: Intended Audience :: Developers
Classifier: License :: OSI Approved :: GNU General Public License v3 (GPLv3)
Classifier: Programming Language :: Python :: 3
Classifier: Programming Language :: Python :: 3.10
Classifier: Programming Language :: Python :: 3.11
Classifier: Programming Language :: Python :: 3.12
Classifier: Programming Language :: Python :: 3.13
Requires-Python: >=3.10
License-File: LICENSE.txt
